pymysqlite.py
pymysqlite-0.0.3.dist-info/METADATA
pymysqlite-0.0.3.dist-info/WHEEL
pymysqlite-0.0.3.dist-info/top_level.txt
pymysqlite-0.0.3.dist-info/RECORD
