Metadata-Version: 2.1
Name: pymysqlite
Version: 0.0.3
Summary: A library that allows testing of code using pymysql without a running MySQL server
Home-page: https://github.com/lubomir-brindza/pymysqlite
Author: Lubomir Brindza
Author-email: lubomir@brindza.sk
Classifier: Programming Language :: Python :: 3
Classifier: Programming Language :: Python :: 3 :: Only
Requires-Python: >=3.8
